mercury_bank_api/__init__.py
mercury_bank_api/mercury_client.py
mercury_bank_api/models/__init__.py
mercury_bank_api/models/account.py
mercury_bank_api/models/transaction.py
mercury_bank_api-1.0.3.dist-info/licenses/LICENSE
mercury_bank_api-1.0.3.dist-info/METADATA
mercury_bank_api-1.0.3.dist-info/WHEEL
mercury_bank_api-1.0.3.dist-info/top_level.txt
mercury_bank_api-1.0.3.dist-info/RECORD
