Metadata-Version: 2.4
Name: mercury_bank_api
Version: 1.0.3
Summary: A comprehensive Python client for the Mercury Bank API
Author-email: Justin Kumpe <jakumpe@kumpeapps.com>
Maintainer-email: Justin Kumpe <jakumpe@kumpeapps.com>
License-Expression: MIT
Project-URL: Homepage, https://github.com/KumpeApps/mercury_bank_api-python
Project-URL: Documentation, https://docs.mercury.com/reference
Project-URL: Repository, https://github.com/KumpeApps/mercury_bank_api-python
Project-URL: Bug Tracker, https://github.com/KumpeApps/mercury_bank_api-python/issues
Keywords: mercury,bank,api,banking,transactions,finance
Classifier: Development Status :: 5 - Production/Stable
Classifier: Intended Audience :: Developers
Classifier: Operating System :: OS Independent
Classifier: Programming Language :: Python :: 3
Classifier: Programming Language :: Python :: 3.7
Classifier: Programming Language :: Python :: 3.8
Classifier: Programming Language :: Python :: 3.9
Classifier: Programming Language :: Python :: 3.10
Classifier: Programming Language :: Python :: 3.11
Classifier: Programming Language :: Python :: 3.12
Classifier: Topic :: Office/Business :: Financial
Classifier: Topic :: Software Development :: Libraries :: Python Modules
Requires-Python: >=3.7
License-File: LICENSE
Requires-Dist: requests>=2.25.0
Requires-Dist: python-dateutil>=2.8.0
Requires-Dist: typing-extensions>=4.0.0
Dynamic: license-file
